poetry_btest/__init__.py
poetry_btest-0.1.0.dist-info/WHEEL
poetry_btest-0.1.0.dist-info/METADATA
poetry_btest-0.1.0.dist-info/RECORD
