Metadata-Version: 2.1
Name: poetry-btest
Version: 0.1.0
Summary: 
Author: haicheng.bi
Author-email: haicheng.bi@qunar.com
Requires-Python: >=3.9,<4.0
Classifier: Programming Language :: Python :: 3
Classifier: Programming Language :: Python :: 3.9
Requires-Dist: pendulum (>=2.1.2,<3.0.0)
